csp/__init__.py
csp/admin.py
csp/apps.py
csp/blacklist.py
csp/fixtures/default_rules.json
csp/management/__init__.py
csp/management/commands/__init__.py
csp/management/commands/truncate_csp_reports.py
csp/middleware.py
csp/migrations/0001_initial.py
csp/migrations/0002_cspreportblacklist.py
csp/migrations/0003_csprule_created_at_csprule_modified_at.py
csp/migrations/__init__.py
csp/models.py
csp/policy.py
csp/settings.py
csp/signals.py
csp/templates/csp/diagnostics.txt
csp/urls.py
csp/utils.py
csp/views.py
django_csp_plus-3.3.0.dist-info/METADATA
django_csp_plus-3.3.0.dist-info/WHEEL
django_csp_plus-3.3.0.dist-info/licenses/LICENSE
django_csp_plus-3.3.0.dist-info/RECORD
